{"name": "Offer Passage\nBetween Worlds","nameFontScale": 1.00,"cost": 1,"speed": "fast","range": {  "enabled": true,"text": "{range,1}"},"target":{"enabled": true,"text":"{any_land}"},"effect":"Move up to 4 {dahan} between target land and one of your lands.\n{wide_or}\nThe next time {dahan} would be Destroyed in target land, Destroy 2 fewer {dahan}.","effectFontScale":1.00,"elements":{"sun":true,"moon":true,"fire":false,"air":true,"water":false,"earth":false,"plant":false,"animal":false},"threshold":{"enabled":false,"relativeHeight":0.50,"conditionText":"","effectText":""},"art":{"image":null,"url":"https://sick.oberien.de/imgs/powers/offer_passage_between_worlds.webp","artist":"Moro Rogers","leftOffset":-0.09,"topOffset":0.24,"scale":0.87},"language":"English","meeple":false}
